gmft_locally/__future__init__.py
gmft_locally/__init__.py
gmft_locally/_dataclasses.py
gmft_locally/auto.py
gmft_locally/common.py
gmft_locally/presets.py
gmft_locally/table_captioning.py
gmft_locally/table_detection.py
gmft_locally/table_function.py
gmft_locally/table_function_algorithm.py
gmft_locally/table_visualization.py
gmft_locally/_rich_text/__init__.py
gmft_locally/_rich_text/common.py
gmft_locally/_rich_text/rich_page.py
gmft_locally/algo/__init__.py
gmft_locally/algo/dividers.py
gmft_locally/algo/histogram.py
gmft_locally/detectors/common.py
gmft_locally/detectors/img2table.py
gmft_locally/detectors/tatr.py
gmft_locally/formatters/common.py
gmft_locally/formatters/ditr.py
gmft_locally/formatters/histogram.py
gmft_locally/formatters/tatr.py
gmft_locally/formatters/with_img2table.py
gmft_locally/formatters/with_tabled.py
gmft_locally/pdf_bindings/__init__.py
gmft_locally/pdf_bindings/bindings_pdfium.py
gmft_locally/pdf_bindings/common.py
gmft_locally/pdf_bindings/pdfium.py
gmft_locally-0.4.4.dist-info/LICENSE
gmft_locally-0.4.4.dist-info/WHEEL
gmft_locally-0.4.4.dist-info/METADATA
gmft_locally-0.4.4.dist-info/RECORD
